{
  "url" : "https://github.com/mishmash-io/distributed-computing-stacks/pull/220",
  "project" : "distributed-computing-stacks",
  "projectOrganisation" : "mishmash-io",
  "breakingCommit" : "11654aa337ebef957b835ed3f7bf38736b1d45d8",
  "prAuthor" : "bot",
  "preCommitAuthor" : "human",
  "breakingCommitAuthor" : "bot",
  "updatedDependency" : {
    "dependencyGroupID" : "org.xmlunit",
    "dependencyArtifactID" : "xmlunit-core",
    "previousVersion" : "2.10.3",
    "newVersion" : "2.10.4",
    "dependencyScope" : "compile",
    "versionUpdateType" : "patch",
    "dependencySection" : "dependencyManagement"
  },
  "licenseInfo" : "Apache License 2.0"
}